[
  {
    "ticker": "TSLA",
    "date": "2026-07-23",
    "seed_hex": "7e37e08e3687fbc9",
    "fmp_data": {
      "close": 0.0,
      "volume": 0,
      "rsi": 50.0,
      "macd": "N/A"
    },
    "divination": {
      "lines": [
        7,
        8,
        8,
        7,
        9,
        7
      ],
      "binary": "100111",
      "logs": [
        {
          "yao": 1,
          "change": 1,
          "left": 36,
          "right": 12,
          "left_rem": 4,
          "right_rem": 4,
          "removed": 9,
          "remaining": 40
        },
        {
          "yao": 1,
          "change": 2,
          "left": 12,
          "right": 27,
          "left_rem": 4,
          "right_rem": 3,
          "removed": 8,
          "remaining": 32
        },
        {
          "yao": 1,
          "change": 3,
          "left": 26,
          "right": 5,
          "left_rem": 2,
          "right_rem": 1,
          "removed": 4,
          "remaining": 28
        },
        {
          "yao": 2,
          "change": 1,
          "left": 38,
          "right": 10,
          "left_rem": 2,
          "right_rem": 2,
          "removed": 5,
          "remaining": 44
        },
        {
          "yao": 2,
          "change": 2,
          "left": 21,
          "right": 22,
          "left_rem": 1,
          "right_rem": 2,
          "removed": 4,
          "remaining": 40
        },
        {
          "yao": 2,
          "change": 3,
          "left": 12,
          "right": 27,
          "left_rem": 4,
          "right_rem": 3,
          "removed": 8,
          "remaining": 32
        },
        {
          "yao": 3,
          "change": 1,
          "left": 41,
          "right": 7,
          "left_rem": 1,
          "right_rem": 3,
          "removed": 5,
          "remaining": 44
        },
        {
          "yao": 3,
          "change": 2,
          "left": 16,
          "right": 27,
          "left_rem": 4,
          "right_rem": 3,
          "removed": 8,
          "remaining": 36
        },
        {
          "yao": 3,
          "change": 3,
          "left": 30,
          "right": 5,
          "left_rem": 2,
          "right_rem": 1,
          "removed": 4,
          "remaining": 32
        },
        {
          "yao": 4,
          "change": 1,
          "left": 47,
          "right": 1,
          "left_rem": 3,
          "right_rem": 1,
          "removed": 5,
          "remaining": 44
        },
        {
          "yao": 4,
          "change": 2,
          "left": 28,
          "right": 15,
          "left_rem": 4,
          "right_rem": 3,
          "removed": 8,
          "remaining": 36
        },
        {
          "yao": 4,
          "change": 3,
          "left": 19,
          "right": 16,
          "left_rem": 3,
          "right_rem": 4,
          "removed": 8,
          "remaining": 28
        },
        {
          "yao": 5,
          "change": 1,
          "left": 46,
          "right": 2,
          "left_rem": 2,
          "right_rem": 2,
          "removed": 5,
          "remaining": 44
        },
        {
          "yao": 5,
          "change": 2,
          "left": 37,
          "right": 6,
          "left_rem": 1,
          "right_rem": 2,
          "removed": 4,
          "remaining": 40
        },
        {
          "yao": 5,
          "change": 3,
          "left": 5,
          "right": 34,
          "left_rem": 1,
          "right_rem": 2,
          "removed": 4,
          "remaining": 36
        },
        {
          "yao": 6,
          "change": 1,
          "left": 4,
          "right": 44,
          "left_rem": 4,
          "right_rem": 4,
          "removed": 9,
          "remaining": 40
        },
        {
          "yao": 6,
          "change": 2,
          "left": 33,
          "right": 6,
          "left_rem": 1,
          "right_rem": 2,
          "removed": 4,
          "remaining": 36
        },
        {
          "yao": 6,
          "change": 3,
          "left": 24,
          "right": 11,
          "left_rem": 4,
          "right_rem": 3,
          "removed": 8,
          "remaining": 28
        }
      ]
    },
    "hexagram": {
      "original": {
        "name": "天雷无妄",
        "symbol": "䷘",
        "meaning": "元亨利贞。其匪正有眚，不利有攸往。"
      },
      "moving_lines": [
        5
      ],
      "changed": {
        "name": "火雷噬嗑",
        "symbol": "䷔",
        "meaning": "亨，利用狱。"
      }
    },
    "oracle": {
      "decryption": "天机显示「天雷无妄」之象，元亨利贞。其匪正有眚，不利有攸往。……卦气流转，数据共振于链上。",
      "market_mapping": "TSLA 当前卦象映射盘面，阴阳交替间暗藏玄机。技术面需结合量能验证趋势方向。",
      "action": "Buy",
      "support_level": "N/A",
      "resistance_level": "N/A"
    }
  },
  {
    "ticker": "QQQ",
    "date": "2026-07-23",
    "seed_hex": "1bf04cf1dd78b379",
    "fmp_data": {
      "close": 0.0,
      "volume": 0,
      "rsi": 50.0,
      "macd": "N/A"
    },
    "divination": {
      "lines": [
        6,
        7,
        7,
        8,
        7,
        8
      ],
      "binary": "011010",
      "logs": [
        {
          "yao": 1,
          "change": 1,
          "left": 28,
          "right": 20,
          "left_rem": 4,
          "right_rem": 4,
          "removed": 9,
          "remaining": 40
        },
        {
          "yao": 1,
          "change": 2,
          "left": 36,
          "right": 3,
          "left_rem": 4,
          "right_rem": 3,
          "removed": 8,
          "remaining": 32
        },
        {
          "yao": 1,
          "change": 3,
          "left": 31,
          "right": 0,
          "left_rem": 3,
          "right_rem": 4,
          "removed": 8,
          "remaining": 24
        },
        {
          "yao": 2,
          "change": 1,
          "left": 41,
          "right": 7,
          "left_rem": 1,
          "right_rem": 3,
          "removed": 5,
          "remaining": 44
        },
        {
          "yao": 2,
          "change": 2,
          "left": 32,
          "right": 11,
          "left_rem": 4,
          "right_rem": 3,
          "removed": 8,
          "remaining": 36
        },
        {
          "yao": 2,
          "change": 3,
          "left": 31,
          "right": 4,
          "left_rem": 3,
          "right_rem": 4,
          "removed": 8,
          "remaining": 28
        },
        {
          "yao": 3,
          "change": 1,
          "left": 36,
          "right": 12,
          "left_rem": 4,
          "right_rem": 4,
          "removed": 9,
          "remaining": 40
        },
        {
          "yao": 3,
          "change": 2,
          "left": 12,
          "right": 27,
          "left_rem": 4,
          "right_rem": 3,
          "removed": 8,
          "remaining": 32
        },
        {
          "yao": 3,
          "change": 3,
          "left": 13,
          "right": 18,
          "left_rem": 1,
          "right_rem": 2,
          "removed": 4,
          "remaining": 28
        },
        {
          "yao": 4,
          "change": 1,
          "left": 9,
          "right": 39,
          "left_rem": 1,
          "right_rem": 3,
          "removed": 5,
          "remaining": 44
        },
        {
          "yao": 4,
          "change": 2,
          "left": 10,
          "right": 33,
          "left_rem": 2,
          "right_rem": 1,
          "removed": 4,
          "remaining": 40
        },
        {
          "yao": 4,
          "change": 3,
          "left": 36,
          "right": 3,
          "left_rem": 4,
          "right_rem": 3,
          "removed": 8,
          "remaining": 32
        },
        {
          "yao": 5,
          "change": 1,
          "left": 38,
          "right": 10,
          "left_rem": 2,
          "right_rem": 2,
          "removed": 5,
          "remaining": 44
        },
        {
          "yao": 5,
          "change": 2,
          "left": 27,
          "right": 16,
          "left_rem": 3,
          "right_rem": 4,
          "removed": 8,
          "remaining": 36
        },
        {
          "yao": 5,
          "change": 3,
          "left": 24,
          "right": 11,
          "left_rem": 4,
          "right_rem": 3,
          "removed": 8,
          "remaining": 28
        },
        {
          "yao": 6,
          "change": 1,
          "left": 5,
          "right": 43,
          "left_rem": 1,
          "right_rem": 3,
          "removed": 5,
          "remaining": 44
        },
        {
          "yao": 6,
          "change": 2,
          "left": 12,
          "right": 31,
          "left_rem": 4,
          "right_rem": 3,
          "removed": 8,
          "remaining": 36
        },
        {
          "yao": 6,
          "change": 3,
          "left": 22,
          "right": 13,
          "left_rem": 2,
          "right_rem": 1,
          "removed": 4,
          "remaining": 32
        }
      ]
    },
    "hexagram": {
      "original": {
        "name": "水风井",
        "symbol": "䷯",
        "meaning": "改邑不改井，无丧无得，往来井井。"
      },
      "moving_lines": [
        1
      ],
      "changed": {
        "name": "水天需",
        "symbol": "䷄",
        "meaning": "有孚，光亨，贞吉，利涉大川。"
      }
    },
    "oracle": {
      "decryption": "天机显示「水风井」之象，改邑不改井，无丧无得，往来井井。……卦气流转，数据共振于链上。",
      "market_mapping": "QQQ 当前卦象映射盘面，阴阳交替间暗藏玄机。技术面需结合量能验证趋势方向。",
      "action": "Hold",
      "support_level": "N/A",
      "resistance_level": "N/A"
    }
  },
  {
    "ticker": "NVDA",
    "date": "2026-07-23",
    "seed_hex": "85f88eadd5d012a4",
    "fmp_data": {
      "close": 0.0,
      "volume": 0,
      "rsi": 50.0,
      "macd": "N/A"
    },
    "divination": {
      "lines": [
        8,
        7,
        7,
        7,
        7,
        8
      ],
      "binary": "011110",
      "logs": [
        {
          "yao": 1,
          "change": 1,
          "left": 28,
          "right": 20,
          "left_rem": 4,
          "right_rem": 4,
          "removed": 9,
          "remaining": 40
        },
        {
          "yao": 1,
          "change": 2,
          "left": 38,
          "right": 1,
          "left_rem": 2,
          "right_rem": 1,
          "removed": 4,
          "remaining": 36
        },
        {
          "yao": 1,
          "change": 3,
          "left": 30,
          "right": 5,
          "left_rem": 2,
          "right_rem": 1,
          "removed": 4,
          "remaining": 32
        },
        {
          "yao": 2,
          "change": 1,
          "left": 36,
          "right": 12,
          "left_rem": 4,
          "right_rem": 4,
          "removed": 9,
          "remaining": 40
        },
        {
          "yao": 2,
          "change": 2,
          "left": 30,
          "right": 9,
          "left_rem": 2,
          "right_rem": 1,
          "removed": 4,
          "remaining": 36
        },
        {
          "yao": 2,
          "change": 3,
          "left": 7,
          "right": 28,
          "left_rem": 3,
          "right_rem": 4,
          "removed": 8,
          "remaining": 28
        },
        {
          "yao": 3,
          "change": 1,
          "left": 43,
          "right": 5,
          "left_rem": 3,
          "right_rem": 1,
          "removed": 5,
          "remaining": 44
        },
        {
          "yao": 3,
          "change": 2,
          "left": 7,
          "right": 36,
          "left_rem": 3,
          "right_rem": 4,
          "removed": 8,
          "remaining": 36
        },
        {
          "yao": 3,
          "change": 3,
          "left": 3,
          "right": 32,
          "left_rem": 3,
          "right_rem": 4,
          "removed": 8,
          "remaining": 28
        },
        {
          "yao": 4,
          "change": 1,
          "left": 45,
          "right": 3,
          "left_rem": 1,
          "right_rem": 3,
          "removed": 5,
          "remaining": 44
        },
        {
          "yao": 4,
          "change": 2,
          "left": 19,
          "right": 24,
          "left_rem": 3,
          "right_rem": 4,
          "removed": 8,
          "remaining": 36
        },
        {
          "yao": 4,
          "change": 3,
          "left": 35,
          "right": 0,
          "left_rem": 3,
          "right_rem": 4,
          "removed": 8,
          "remaining": 28
        },
        {
          "yao": 5,
          "change": 1,
          "left": 28,
          "right": 20,
          "left_rem": 4,
          "right_rem": 4,
          "removed": 9,
          "remaining": 40
        },
        {
          "yao": 5,
          "change": 2,
          "left": 4,
          "right": 35,
          "left_rem": 4,
          "right_rem": 3,
          "removed": 8,
          "remaining": 32
        },
        {
          "yao": 5,
          "change": 3,
          "left": 10,
          "right": 21,
          "left_rem": 2,
          "right_rem": 1,
          "removed": 4,
          "remaining": 28
        },
        {
          "yao": 6,
          "change": 1,
          "left": 37,
          "right": 11,
          "left_rem": 1,
          "right_rem": 3,
          "removed": 5,
          "remaining": 44
        },
        {
          "yao": 6,
          "change": 2,
          "left": 35,
          "right": 8,
          "left_rem": 3,
          "right_rem": 4,
          "removed": 8,
          "remaining": 36
        },
        {
          "yao": 6,
          "change": 3,
          "left": 2,
          "right": 33,
          "left_rem": 2,
          "right_rem": 1,
          "removed": 4,
          "remaining": 32
        }
      ]
    },
    "hexagram": {
      "original": {
        "name": "泽风大过",
        "symbol": "䷛",
        "meaning": "栋桡，利有攸往，亨。"
      },
      "moving_lines": [],
      "changed": null
    },
    "oracle": {
      "decryption": "天机显示「泽风大过」之象，栋桡，利有攸往，亨。……卦气流转，数据共振于链上。",
      "market_mapping": "NVDA 当前卦象映射盘面，阴阳交替间暗藏玄机。技术面需结合量能验证趋势方向。",
      "action": "Buy",
      "support_level": "N/A",
      "resistance_level": "N/A"
    }
  }
]